StrainFlair-0.0.2.data/scripts/StrainFLAIR.sh
strainflair/__init__.py
strainflair/__main__.py
strainflair/compute_strains_abundance.py
strainflair/concat_graphs.py
strainflair/genes_prediction.py
strainflair/graphs_construction.py
strainflair/json2csv.py
StrainFlair-0.0.2.dist-info/LICENSE
StrainFlair-0.0.2.dist-info/METADATA
StrainFlair-0.0.2.dist-info/WHEEL
StrainFlair-0.0.2.dist-info/entry_points.txt
StrainFlair-0.0.2.dist-info/top_level.txt
StrainFlair-0.0.2.dist-info/RECORD
