Metadata-Version: 2.1
Name: StrainFlair
Version: 0.0.2
Summary: StrainFLAIR (STRAIN-level proFiLing using vArIation gRaph) is a tool for strain identification and quantification that uses variation graph representation of genes sequences
Home-page: https://github.com/kevsilva/StrainFLAIR
Author: Kévin Da Sylva - Pierre Peterlongo
Author-email: Kevin.Da-Silva@inria.fr, pierre.peterlongo@inria.fr
License: UNKNOWN
Platform: UNKNOWN
Requires-Dist: pandas (>=1.2.1)
Requires-Dist: Bio (>=0.3.0)
